emoprint/__init__.py
emoprint/emolist.txt
emoprint/emoprint.py
emoprint-0.1.1.dist-info/WHEEL
emoprint-0.1.1.dist-info/METADATA
emoprint-0.1.1.dist-info/RECORD
